nullus/__init__.py
nullus/main.py
nullus-1.0.5.dist-info/METADATA
nullus-1.0.5.dist-info/WHEEL
nullus-1.0.5.dist-info/entry_points.txt
nullus-1.0.5.dist-info/licenses/LICENSE
nullus-1.0.5.dist-info/RECORD
