Metadata-Version: 2.4
Name: nullus
Version: 1.0.5
Summary: Task management in the CLI
Project-URL: Repository, https://github.com/plwg/nullus
Author-email: plwg <56353330+plwg@users.noreply.github.com>
License-Expression: MIT
License-File: LICENSE
Keywords: GTD,cli
Classifier: Development Status :: 4 - Beta
Classifier: Environment :: Console
Classifier: Operating System :: OS Independent
Classifier: Programming Language :: Python :: 3
Requires-Python: >=3.9
Requires-Dist: polars>=1.26.0
